module_exports/__init__.py
module_exports-1.1.0.dist-info/LICENSE
module_exports-1.1.0.dist-info/METADATA
module_exports-1.1.0.dist-info/WHEEL
module_exports-1.1.0.dist-info/top_level.txt
module_exports-1.1.0.dist-info/RECORD
