Metadata-Version: 2.1
Name: module-exports
Version: 1.1.0
Summary: One decorator to export them __all__ :)
Home-page: https://github.com/ramon93i7/module_exports
Author: Roman Shemyakin
Author-email: ramon93i7@gmail.com
License: UNKNOWN
Platform: UNKNOWN
Classifier: Programming Language :: Python :: 3
Classifier: License :: OSI Approved :: MIT License
Classifier: Operating System :: OS Independent
Requires-Python: >=3.6
